[
    {
        "nomorBN": 279,
        "versi": "A",
        "judul": "BN 279A SERAHKAN SEMUANYA",
        "judul_asli": "Pasahat Ma Sudena (BL No. 160)",
        "nada_dasar": "1=Es 4/4",
        "baits": [
            {
                "nomor_bait": "1",
                "lirik": [
                    "Serahkan semuanya, duka, kuatirmu",
                    "Kepada Allah Bapa yang mengasihimu",
                    "Bukankah kuasa-Nya segenap bumi, laut",
                    "Manusia berencana, Tuhanlah penentu"
                ]
            },
            {
                "nomor_bait": "2",
                "lirik": [
                    "Engkau harus percaya kepada Tuhanmu",
                    "Supaya kau terima rencana hatimu",
                    "Kar’na tiada gunanya kuatirmu semua",
                    "Berdoalah pada-Nya agar kau bahagia"
                ]
            },
            {
                "nomor_bait": "3",
                "lirik": [
                    "Dia pasti memahami s’gala rancanganmu",
                    "Yang jahat dan yang baik di dalam hatimu",
                    "Dan Tuhan kehendaki yang baik bagimu",
                    "Yang jahat disingkirkan menjaga hidupmu"
                ]
            },
            {
                "nomor_bait": "4",
                "lirik": [
                    "Tetaplah kau setia kepada Tuhanmu",
                    "Jauhkanlah semua segala kuatirmu",
                    "Jika tekun dan tabah dalam deritamu",
                    "Dia segera ‘kan datang menghibur hatimu"
                ]
            },
            {
                "nomor_bait": "5",
                "lirik": [
                    "Serahkanlah dirimu kepada Tuhan-Mu",
                    "Kar’na Dia penuh hikmat mencipta semua",
                    "Apakah Dia tak mampu ‘tuk melepaskanmu?",
                    "Hendak dinyatakan-Nya, bagimu kuasa-Nya"
                ]
            },
            {
                "nomor_bait": "6",
                "lirik": [
                    "Ya Tuhan ‘ku mohonkan, akhirilah semua",
                    "Segala kesedihan, sengsara pun juga",
                    "Terima kami Tuhan, umat-Mu yang resah",
                    "Kau tuntun masuk Surga, ke tempat bahagia"
                ]
            }
        ]
    },
    {
        "nomorBN": 279,
        "versi": "B",
        "judul": "BN 279B SERAHKAN SEMUANYA",
        "judul_asli": "Pasahat Ma Sudena (BL No. 160B)",
        "nada_dasar": "1=Es 4/4",
        "baits": [
            {
                "nomor_bait": "1",
                "lirik": [
                    "Serahkan semuanya duka, kuatirmu",
                    "Kepada Allah Bapa yang mengasihimu",
                    "Bukankah kuasa-Nya segenap bumi, laut",
                    "Manusia berencana, Tuhanlah penentu"
                ]
            },
            {
                "nomor_bait": "2",
                "lirik": [
                    "Engkau harus percaya kepada Tuhanmu",
                    "Supaya kau terima rencana hatimu",
                    "Kar’na tiada gunanya kuatirmu semua",
                    "Berdoalah pada-Nya agar kau bahagia"
                ]
            },
            {
                "nomor_bait": "3",
                "lirik": [
                    "Dia pasti memahami s’gala rancanganmu",
                    "Yang jahat dan yang baik di dalam hatimu",
                    "Dan Tuhan kehendaki yang baik bagimu",
                    "Yang jahat disingkirkan menjaga hidupmu"
                ]
            },
            {
                "nomor_bait": "4",
                "lirik": [
                    "Tetaplah kau setia kepada Tuhanmu",
                    "Jauhkanlah semua segala kuatirmu",
                    "Jika tekun dan tabah dalam deritamu",
                    "Dia segera ‘kan datang menghibur hatimu"
                ]
            },
            {
                "nomor_bait": "5",
                "lirik": [
                    "Serahkanlah dirimu kepada Tuhan-Mu",
                    "Kar’na Dia penuh hikmat mencipta semua",
                    "Apakah Dia tak mampu ‘tuk melepaskanmu?",
                    "Hendak dinyatakan-Nya, bagimu kuasa-Nya"
                ]
            },
            {
                "nomor_bait": "6",
                "lirik": [
                    "Ya Tuhan ‘ku mohonkan, akhirilah semua",
                    "Segala kesedihan, sengsara pun juga",
                    "Terima kami Tuhan, umat-Mu yang resah",
                    "Kau tuntun masuk Surga, ke tempat bahagia"
                ]
            }
        ]
    },
    {
        "nomorBN": 568,
        "versi": "A",
        "judul": "BN 568A SEMUA SUARA BERNYANYI (1)",
        "judul_asli": "Nasa Soara Ingkon Do (1) (BL No. 568A)",
        "nada_dasar": "1=As 3/2",
        "baits": [
            {
                "nomor_bait": "1",
                "lirik": [
                    "Semua suara bernyanyi memuji Tuhanku",
                    "Memberitakan kuasaMu dengan kidung merdu"
                ]
            },
            {
                "nomor_bait": "2",
                "lirik": [
                    "Kuatkan hambaMu Tuhan memb’ri kesaksian",
                    "Sampai ke ujing dunia Dikau ‘ku masyhurkan"
                ]
            },
            {
                "nomor_bait": "3",
                "lirik": [
                    "Ya Yesus, agung kasihMu hiburkan hatiku",
                    "Sembuhkanlah sakit hatiku, pulihkan hidupku"
                ]
            },
            {
                "nomor_bait": "4",
                "lirik": [
                    "Kuasa iblis seteru sudah Kau kalahkan",
                    "Dosaku sudah Kau tebus, jiwaku pun tent’ram"
                ]
            },
            {
                "nomor_bait": "5",
                "lirik": [
                    "Hai umat dengar FirmanNya, taatilah Dia",
                    "Hidupmu akan bahagia selama-lamanya"
                ]
            },
            {
                "nomor_bait": "6",
                "lirik": [
                    "Yang tuli dapat mendengar, yang lumpuh berjalan",
                    "Yang mati dibangkitkanNya oleh Kristus Tuhan"
                ]
            }
        ]
    },
    {
        "nomorBN": 568,
        "versi": "B",
        "judul": "BN 568B SEMUA SUARA BERNYANYI (2)",
        "judul_asli": "Nasa Soara Ingkon Do (BL No. 568B)",
        "nada_dasar": "1=G 2/2",
        "baits": [
            {
                "nomor_bait": "1",
                "lirik": [
                    "Semua suara bernyanyi memuji Tuhanku",
                    "Memuji Tuhanku memberitakan kuasaMu",
                    "Dengan kidung merdu, dengan kidung merdu",
                    "Dengan kidung merdu"
                ]
            },
            {
                "nomor_bait": "2",
                "lirik": [
                    "Kuatkan hambaMu Tuhan, memb’ri kesaksian",
                    "Memb’ri kesaksian sampai ke ujing dunia",
                    "Dikau ‘ku masyhurkan, Dikau ‘ku masyhurkan",
                    "Dikau ‘ku masyhurkan"
                ]
            },
            {
                "nomor_bait": "3",
                "lirik": [
                    "Ya Yesus agung kasihMu hiburkan hatiku",
                    "Hiburkan hatiku, sembuhkan sakit hatiku",
                    "Pulihkan hidupku, pulihkan hidupku",
                    "Pulihkan hidupku"
                ]
            },
            {
                "nomor_bait": "4",
                "lirik": [
                    "Kuasa iblis seteru sudah Kau kalahkan",
                    "Sudah Kau kalahkan, dosaku sudah Kau tebus",
                    "Jiwaku pun tent’ram, jiwaku pun tent’ram",
                    "Jiwaku pun tent’ram"
                ]
            },
            {
                "nomor_bait": "5",
                "lirik": [
                    "Hai umat dengar FirmanNya, taatilah dia",
                    "Taatilah Dia hidupmu akan bahagia",
                    "Selama-lamanya, selama-lamanya",
                    "Selama-lamanya"
                ]
            },
            {
                "nomor_bait": "6",
                "lirik": [
                    "Yang tuli dapat mendengar, yang lumpuh berjalan",
                    "Yang lumpuh berjalan, yang mati dibangkitkanNya",
                    "Oleh Kristus Tuhan, oleh Kristus Tuhan",
                    "Oleh Kristus Tuhan"
                ]
            }
        ]
    },
    {
        "nomorBN": 597,
        "versi": "A",
        "judul": "BN 597A HAI B’RITAKAN DI GUNUNG (1)",
        "judul_asli": "Baritahon Di Dolok (BL No. 597a)",
        "nada_dasar": "1=As 4/4",
        "baits": [
            {
                "nomor_bait": "Tidak ada nomor bait",
                "lirik": []
            },
            {
                "nomor_bait": "1",
                "lirik": [
                    "Hai, b’ritakan di gunung, di lembah dan di mana juga",
                    "Hai, b’ritakan di gunung, t’lah lahir Penebus",
                    "Ketika ‘ku mencari di siang, malam pun",
                    "Bahagia yang sejati, Kau tuntun jalanku"
                ]
            }
        ]
    },
    {
        "nomorBN": 597,
        "versi": "B",
        "judul": "BN 597B HAI B’RITAKAN DI GUNUNG (2)",
        "judul_asli": "Baritahon Di Dolok (2) (BL No. 597b)",
        "nada_dasar": "1=As 4/4",
        "baits": [
            {
                "nomor_bait": "Tidak ada nomor bait",
                "lirik": []
            },
            {
                "nomor_bait": "1",
                "lirik": [
                    "Hai, b’ritakan di gunung, di lembah dan di mana juga",
                    "Hai, b’ritakan di gunung, t’lah lahir Penebus"
                ]
            },
            {
                "nomor_bait": "1",
                "lirik": [
                    "Malaikat Surga datang dengan cahaya t’rang",
                    "Menyapa kaum gembala di ladang Efrata"
                ]
            },
            {
                "nomor_bait": "2",
                "lirik": [
                    "Gembala ketakutan, melihat sinar t’rang",
                    "Malaikat dari Surga nyanyikan pujian"
                ]
            },
            {
                "nomor_bait": "3",
                "lirik": [
                    "Terbaring di palungan di kandang yang hina",
                    "Seperti dib’ritakan para malaikatNya"
                ]
            }
        ]
    },
    {
        "nomorBN": 603,
        "versi": "A",
        "judul": "BN 603A DI DALAM PALUNGAN (1)",
        "judul_asli": "Di Panggagatan I (BL No. 603a)",
        "nada_dasar": "1=F 3/4",
        "baits": [
            {
                "nomor_bait": "1",
                "lirik": [
                    "Di dalam palungan Kau tidur Tuhan",
                    "Meski lahir miskin hatiMu senang",
                    "BintangMu di langit bersinar terang",
                    "Melihat Kau Tuhan yang tidur tenang"
                ]
            },
            {
                "nomor_bait": "2",
                "lirik": [
                    "Walau ternak domba mengganggu Dikau",
                    "Tetapi Yesusku tenang terlelap",
                    "Hatiku, jiwaku mengasihiMu",
                    "Kau Tuhan sertaku di malam kelam"
                ]
            },
            {
                "nomor_bait": "3",
                "lirik": [
                    "Ya, Yesus Tuhanku Kaulah sertaku",
                    "Dengarlah doaku beri berkatMu",
                    "Semua umatMu, Kau pimpin Tuhan",
                    "Berjalan ke Surga rumah yang baka"
                ]
            }
        ]
    },
    {
        "nomorBN": 603,
        "versi": "B",
        "judul": "BN 603B DI DALAM PALUNGAN (2)",
        "judul_asli": "Di Panggagatan I (2) (BL No. 603b)",
        "nada_dasar": "1=F 3/4",
        "baits": [
            {
                "nomor_bait": "1",
                "lirik": [
                    "Di dalam palungan Kau tidur Tuhan",
                    "Meski lahir miskin hatiMu senang",
                    "BintangMu di langit bersinar terang",
                    "Melihat Kau Tuhan yang tidur tenang"
                ]
            },
            {
                "nomor_bait": "2",
                "lirik": [
                    "Walau ternak domba mengganggu Dikau",
                    "Tetapi Yesusku tenang terlelap",
                    "Hatiku, jiwaku mengasihiMu",
                    "Kau Tuhan sertaku di malam kelam"
                ]
            },
            {
                "nomor_bait": "3",
                "lirik": [
                    "Ya, Yesus Tuhanku Kaulah sertaku",
                    "Dengarlah doaku beri berkatMu",
                    "Semua umatMu, Kau pimpin Tuhan"
                ]
            }
        ]
    },
    {
        "nomorBN": 637,
        "versi": "A",
        "judul": "BN 637A AGUNGKANLAH KUASA",
        "judul_asli": "Patimbul Ma Huaso Ni Goar Ni Jesus (1) (BL No. 637A)",
        "nada_dasar": "1=G 4/4",
        "baits": [
            {
                "nomor_bait": "1",
                "lirik": [
                    "Agungkanlah kuasa Yesus, soraklah",
                    "Muliakanlah Tuhan kita, pujilah namaNya",
                    "Muliakanlah Tuhan kita, muliakanlah Tuhan kita"
                ]
            },
            {
                "nomor_bait": "2",
                "lirik": [
                    "Hai semua bintang yang terang, bersoraklah terus",
                    "Agungkan Dia yang menang, pujilah namaNya",
                    "Agungkan Dia yang menang, muliakanlah Tuhan kita"
                ]
            },
            {
                "nomor_bait": "3",
                "lirik": [
                    "Kaum Israel yang dipilihNya, agungkanlah Tuhan",
                    "Mesiasmu terimalah, pujilah namaNya",
                    "Mesiasmu terimalah, muliakanlah Tuhan kita"
                ]
            },
            {
                "nomor_bait": "4",
                "lirik": [
                    "Jemaat yang dis’lamatkanNya, ingatlah Tuhanmu",
                    "Derita yang ditanggungNya untuk menebusmu",
                    "Derita yang ditanggungNya, muliakanlah Tuhan kita"
                ]
            },
            {
                "nomor_bait": "5",
                "lirik": [
                    "Yang martir berbahagialah karena imannya",
                    "Yang mau memikul salibnya, pujilah namaNya",
                    "Yang mau memikul salibnya, muliakanlah Tuhan kita"
                ]
            },
            {
                "nomor_bait": "6",
                "lirik": [
                    "Pewaris kerajaanNya, bersukacitalah",
                    "Taatilah perintahNya, pujilah namaNya",
                    "Taatilah perintahNya, muliakanlah Tuhan kita"
                ]
            },
            {
                "nomor_bait": "7",
                "lirik": [
                    "Hai bangsa-bangsa dunia, sujudlah menyembah",
                    "Sambutlah kerajaanNya, pujilah namaNya",
                    "Sambutlah kerajaanNya, muliakanlah Tuhan kita"
                ]
            },
            {
                "nomor_bait": "8",
                "lirik": [
                    "Bersama-sama yang menang di Surga nantinya",
                    "Di sana kita bernyanyi memuji namaNya",
                    "Di sana kita bernyanyi, muliakanlah Tuhan kita"
                ]
            }
        ]
    },
    {
        "nomorBN": 637,
        "versi": "B",
        "judul": "BN 637B AGUNGKANLAH KUASA",
        "judul_asli": "Patimbul Ma Huaso Ni Goar Ni Jesus (2) (BL No. 637B)",
        "nada_dasar": "1=A 4/4",
        "baits": [
            {
                "nomor_bait": "1",
                "lirik": [
                    "Agungkanlah kuasaNya, hai umat soraklah",
                    "Muliakanlah Tuhan kita",
                    "Dan hormat, hormat, hormat, muliakan Tuhan"
                ]
            },
            {
                "nomor_bait": "2",
                "lirik": [
                    "Hai semua bintang yang terang, bersorak-soraklah",
                    "Agungkan Dia yang menang",
                    "Dan hormat, hormat, hormat, muliakan Tuhan"
                ]
            },
            {
                "nomor_bait": "3",
                "lirik": [
                    "Kaum Israel yang dipilihNya, agungkanlah Tuhan",
                    "Mesiasmu terimalah",
                    "Dan hormat, hormat, hormat, muliakan Tuhan"
                ]
            },
            {
                "nomor_bait": "4",
                "lirik": [
                    "Jemaat yang dis’lamatkanNya, ingat deritaNya",
                    "Dia mencurahkan darahNya",
                    "Dan hormat, hormat, hormat, muliakan Tuhan"
                ]
            },
            {
                "nomor_bait": "5",
                "lirik": [
                    "Yang martir berbahagialah karena imannya",
                    "Yang mau memikul salibnya",
                    "Dan hormat, hormat, hormat, muliakan Tuhan"
                ]
            },
            {
                "nomor_bait": "6",
                "lirik": [
                    "Pewaris kerajaanNya, bersukacitalah",
                    "Taatilah perintahNya",
                    "Dan hormat, hormat, hormat, muliakan Tuhan"
                ]
            },
            {
                "nomor_bait": "7",
                "lirik": [
                    "Hai bangsa-bangsa dunia, sujudlah menyembah",
                    "Sambutlah kerajaanNya",
                    "Dan hormat, hormat, hormat, muliakan Tuhan"
                ]
            },
            {
                "nomor_bait": "8",
                "lirik": [
                    "Bersama-sama yang menang di Surga nantinya",
                    "Di sana kita bernyanyi",
                    "Dan hormat, hormat, hormat, muliakan Tuhan"
                ]
            }
        ]
    },
    {
        "nomorBN": 641,
        "versi": "A",
        "judul": "BN 641A YA ROH KUDUS B’RI (1)",
        "judul_asli": "O Tondoi Parbadia (1) (BL No. 641A)",
        "nada_dasar": "1=F 3/4",
        "baits": [
            {
                "nomor_bait": "1",
                "lirik": [
                    "Ya Roh Kudus b’ri hikmatMu, penuhilah umatMu",
                    "Pohon di hutan bertepuk, ombak di laut bergemuruh",
                    "Semua ciptaanMu bersorak-sorai bagiMu",
                    "Nyanyikan Haleluya"
                ]
            },
            {
                "nomor_bait": "2",
                "lirik": [
                    "Ya Roh Kudus tahbiskanlah nabiMu dan pelayan",
                    "Nyatakanlah kasihMu Tuhan untuk orang tertindas",
                    "Jauhkanlah kuasa g’lap, iman jemaat kobarkanlah",
                    "Soraklah Haleluya"
                ]
            },
            {
                "nomor_bait": "3",
                "lirik": [
                    "Ya Allah Bapa, Anak, Roh yang memb’ri kehidupan",
                    "Penuhi kamu dengan Roh masyhurkan Injil Tuhan",
                    "Kristus tercurah darahNya menebus umat manusia",
                    "Nyanyikan Haleluya"
                ]
            },
            {
                "nomor_bait": "4",
                "lirik": [
                    "Ya Roh Kudus penuhilah bumi dan cakrawala",
                    "KerajaanMu datanglah bagi semua bangsa",
                    "Pimpinlah umatMu Tuhan sampai ke Surga yang baka"
                ]
            }
        ]
    },
    {
        "nomorBN": 641,
        "versi": "B",
        "judul": "BN 641B YA ROH KUDUS B’RI",
        "judul_asli": "O Tondi Parbadia (2) (BL No. 641B)",
        "nada_dasar": "1=F 4/4",
        "baits": [
            {
                "nomor_bait": "1",
                "lirik": [
                    "Ya Roh Kudus b’ri hikmatMu, penuhi umatMu",
                    "Nyalakan api s’mangatku b’ritakan InjilMu"
                ]
            },
            {
                "nomor_bait": "2",
                "lirik": [
                    "T’lah Kau ilhami hambaMu menulis Alkitab",
                    "Berilah kami hikmatMu ‘tuk memahaminya"
                ]
            },
            {
                "nomor_bait": "3",
                "lirik": [
                    "Roh Tuhan Allah datanglah berilah sinar t’rang",
                    "Sinari hati yang resah b’ri damai bahagia"
                ]
            },
            {
                "nomor_bait": "4",
                "lirik": [
                    "Dengan Roh KudusMu Tuhan, umatMu mengenal",
                    "Sang Allah Bapa di Surga dan Yesus PutraNya"
                ]
            }
        ]
    },
    {
        "nomorBN": 738,
        "versi": "A",
        "judul": "BN 738A DEKAT KEPADAMU",
        "judul_asli": "Lam Jonok Rohangki (1) (BL No. 738a)",
        "nada_dasar": "1=G 6/4",
        "baits": [
            {
                "nomor_bait": "1",
                "lirik": [
                    "Dekat kepadaMu, ya Tuhanku",
                    "B’rikanlah tanganMu peganganku",
                    "Bidukku mau tengg’lam di lautan yang dalam",
                    "Bawalah jiwaku kepadaMu"
                ]
            },
            {
                "nomor_bait": "2",
                "lirik": [
                    "Dekat kepadaMu, ya Tuhanku",
                    "Biarlah salibMu ku ingat t’rus",
                    "DarahMu yang kudus menghapus dosaku",
                    "Ajaiblah kasihMu kepadaku"
                ]
            },
            {
                "nomor_bait": "3",
                "lirik": [
                    "Dekat kepadaMu, ya Tuhanku",
                    "Aku melangkah t’rus ke rumahMu",
                    "Di sana jiwaku serta malaikatMu",
                    "Memuji namaMu di SurgaMu"
                ]
            }
        ]
    },
    {
        "nomorBN": 738,
        "versi": "B",
        "judul": "BN 738B MAKIN DEKAT TUHAN",
        "judul_asli": "Lam Jonok Rohangki (2) (BL No. 738b)",
        "nada_dasar": "1=G 6/4",
        "baits": [
            {
                "nomor_bait": "1",
                "lirik": [
                    "Makin dekat Tuhan kepadaMu",
                    "Dan jalan saliblah yang ‘ku tempuh",
                    "Inilah kidungku, dekat kepadaMu",
                    "Makin dekat Tuhan kepadaMu"
                ]
            },
            {
                "nomor_bait": "2",
                "lirik": [
                    "Berbantal batu pun, aku senang",
                    "Walau dunia kelam hatiku t’rang",
                    "Asalkan mimpiku dekat kepadaMu",
                    "Makin dekat Tuhan kepadaMu"
                ]
            },
            {
                "nomor_bait": "3",
                "lirik": [
                    "Terangi jalanku ke rumahMu",
                    "Berikan berkatMu dan rahmatMu",
                    "Dan para malakMu dekatkan hatiku",
                    "Makin dekat Tuhan kepadaMu"
                ]
            },
            {
                "nomor_bait": "4",
                "lirik": [
                    "Walau makin berat deritaku",
                    "Semua ‘ku gunakan memujiMu",
                    "Bangunkan jiwaku menyanyi untukMu",
                    "Makin dekat Tuhan kepadaMu"
                ]
            },
            {
                "nomor_bait": "5",
                "lirik": [
                    "Walau makin renta usiaku",
                    "‘Ku ingin mau terbang ke SurgaMu",
                    "Inilah laguku dekat kepadaMu",
                    "Makin dekat Tuhan kepadaMu"
                ]
            }
        ]
    },
    {
        "nomorBN": 796,
        "versi": "A",
        "judul": "BN 796A KASIH SETIANYA",
        "judul_asli": "Asi Ni RohaNa (BL No. 796a)",
        "nada_dasar": "1=G 4/4",
        "baits": [
            {
                "nomor_bait": "1",
                "lirik": [
                    "Kasih setiaNya yang membawa kau",
                    "Kasih selamanya tetap bagimu"
                ]
            },
            {
                "nomor_bait": "2",
                "lirik": [
                    "Tuhan menggenapi janji setiaNya",
                    "Kau ‘kan dipuaskan oleh rahmatNya"
                ]
            },
            {
                "nomor_bait": "3",
                "lirik": [
                    "Tuhan Allah Bapa yang memangkumu",
                    "Sampai masa tua Dia menggendongmu"
                ]
            },
            {
                "nomor_bait": "4",
                "lirik": [
                    "Sejak di kandungan kau dipangkuNya",
                    "Kasih Tuhan nyata tiada akhirnya"
                ]
            }
        ]
    },
    {
        "nomorBN": 796,
        "versi": "B",
        "judul": "BN 796B KASIH SETIAMU",
        "judul_asli": "Asi Ni RohaM Do (BL No. 797b)",
        "nada_dasar": "1=F 4/4",
        "baits": [
            {
                "nomor_bait": "1",
                "lirik": [
                    "Kasih setiaMu yang menggendongku",
                    "Sampai di rumahMu nyata kasihMu"
                ]
            },
            {
                "nomor_bait": "2",
                "lirik": [
                    "Dari masa muda hingga tua pun",
                    "Kau tetap menjaga aku anakMu"
                ]
            },
            {
                "nomor_bait": "3",
                "lirik": [
                    "Pasti Kau nyatakan kasih setiaMu",
                    "Kau menggendong aku kar’na kasihMu"
                ]
            },
            {
                "nomor_bait": "4",
                "lirik": [
                    "Engkau Jurus’lamat bagi diriku",
                    "Tak Kau kecewakan jemaat G’rejaMu"
                ]
            },
            {
                "nomor_bait": "5",
                "lirik": [
                    "Yang pergi dahulu t’lah bersamaMu",
                    "Di Surga RumahMu dapat rahmatMu"
                ]
            },
            {
                "nomor_bait": "6",
                "lirik": [
                    "Aku tak kuatir dalam hidupku",
                    "Semua ‘kan terjadi sesuai firmanMu"
                ]
            },
            {
                "nomor_bait": "7",
                "lirik": [
                    "S’perti masa muda, kau dipangkuNya",
                    "Kasih Tuhan nyata s’lama-lamanya"
                ]
            }
        ]
    },
    {
        "nomorBN": 844,
        "versi": "A",
        "judul": "BN 844A AMIN, AMIN, AMIN",
        "judul_asli": "Amen, Amen, Amen (BL No.844a)",
        "nada_dasar": "1=Es 4/4",
        "baits": [
            {
                "nomor_bait": "1",
                "lirik": [
                    "A – min, Amin, Amin"
                ]
            }
        ]
    },
    {
        "nomorBN": 844,
        "versi": "B",
        "judul": "BN 844B AMIN, AMIN, AMIN",
        "judul_asli": "Amen, Amen, Amen (BL No. 844b)",
        "nada_dasar": "1=G 2/4",
        "baits": [
            {
                "nomor_bait": "1",
                "lirik": [
                    "Amin, Amin, A – min."
                ]
            }
        ]
    }
]